hoshi/__init__.py
hoshi/i18n.py
hoshi/messages.py
hoshi/sets.py
hoshi/translation.py
hoshi/translators/__init__.py
hoshi/translators/base.py
hoshi/translators/gcloud.py
tests/__init__.py
tests/coveralls.py
hoshi-0.4.4.dist-info/LICENSE
hoshi-0.4.4.dist-info/METADATA
hoshi-0.4.4.dist-info/WHEEL
hoshi-0.4.4.dist-info/top_level.txt
hoshi-0.4.4.dist-info/RECORD
