Metadata-Version: 2.1
Name: hoshi
Version: 0.4.4
Summary: Python i18n for human beings
Home-page: https://github.com/chintal/hoshi
Author: Chintalagiri Shashank
Author-email: shashank.chintalagiri@gmail.com
License: UNKNOWN
Project-URL: Documentation, https://hoshi.readthedocs.io/en/latest
Project-URL: Bug Tracker, https://github.com/chintal/hoshi/issues
Project-URL: Source Repository, https://github.com/chintal/hoshi
Platform: any
Classifier: Development Status :: 4 - Beta
Classifier: Intended Audience :: Developers
Classifier: License :: OSI Approved :: MIT License
Classifier: Programming Language :: Python
Classifier: Programming Language :: Python :: 3 :: Only
Classifier: Topic :: Software Development :: Localization
Requires-Python: >=3.7
Requires-Dist: babel
Requires-Dist: setuptools-scm
Requires-Dist: google-cloud-translate
Requires-Dist: wheel
Provides-Extra: build
Requires-Dist: setuptools-scm ; extra == 'build'
Requires-Dist: sphinx ; extra == 'build'
Requires-Dist: alabaster ; extra == 'build'
Requires-Dist: tox ; extra == 'build'
Requires-Dist: tox-pyenv ; extra == 'build'
Requires-Dist: pytest-sphinx ; extra == 'build'
Requires-Dist: pytest ; extra == 'build'
Requires-Dist: pytest-flake8 ; extra == 'build'
Requires-Dist: pytest-cov ; extra == 'build'
Requires-Dist: coveralls[yaml] ; extra == 'build'
Provides-Extra: dev
Requires-Dist: setuptools-scm ; extra == 'dev'
Requires-Dist: sphinx ; extra == 'dev'
Requires-Dist: alabaster ; extra == 'dev'
Requires-Dist: tox ; extra == 'dev'
Requires-Dist: tox-pyenv ; extra == 'dev'
Requires-Dist: pytest-sphinx ; extra == 'dev'
Requires-Dist: pytest ; extra == 'dev'
Requires-Dist: pytest-flake8 ; extra == 'dev'
Requires-Dist: pytest-cov ; extra == 'dev'
Requires-Dist: coveralls[yaml] ; extra == 'dev'
Provides-Extra: docs
Requires-Dist: setuptools-scm ; extra == 'docs'
Requires-Dist: sphinx ; extra == 'docs'
Requires-Dist: alabaster ; extra == 'docs'
Provides-Extra: publish
Requires-Dist: setuptools-scm ; extra == 'publish'
Requires-Dist: sphinx ; extra == 'publish'
Requires-Dist: alabaster ; extra == 'publish'
Requires-Dist: tox ; extra == 'publish'
Requires-Dist: tox-pyenv ; extra == 'publish'
Requires-Dist: pytest-sphinx ; extra == 'publish'
Requires-Dist: pytest ; extra == 'publish'
Requires-Dist: pytest-flake8 ; extra == 'publish'
Requires-Dist: pytest-cov ; extra == 'publish'
Requires-Dist: coveralls[yaml] ; extra == 'publish'
Requires-Dist: twine ; extra == 'publish'
Requires-Dist: pygithub ; extra == 'publish'
Provides-Extra: tests
Requires-Dist: setuptools-scm ; extra == 'tests'
Requires-Dist: sphinx ; extra == 'tests'
Requires-Dist: alabaster ; extra == 'tests'
Requires-Dist: tox ; extra == 'tests'
Requires-Dist: tox-pyenv ; extra == 'tests'
Requires-Dist: pytest-sphinx ; extra == 'tests'
Requires-Dist: pytest ; extra == 'tests'
Requires-Dist: pytest-flake8 ; extra == 'tests'
Requires-Dist: pytest-cov ; extra == 'tests'
Requires-Dist: coveralls[yaml] ; extra == 'tests'
